xswap-0.0.2.dist-info/WHEEL
xswap-0.0.2.dist-info/top_level.txt
xswap-0.0.2.dist-info/METADATA
xswap-0.0.2.dist-info/RECORD
xswap/permute.py
xswap/__init__.py
xswap/network_formats.py
xswap/preprocessing.py
xswap/_xswap_backend.cpython-35m-x86_64-linux-gnu.so
xswap/prior.py
