Metadata-Version: 2.1
Name: xswap
Version: 0.0.2
Summary: Python-wrapped C/C++ library for degree-preserving network randomization
Home-page: https://github.com/greenelab/xswap
Author: Michael Zietz
Author-email: michael.zietz@gmail.com
License: BSD 2-Clause
Platform: UNKNOWN
Requires-Python: >=3.5
